devinterp/__init__.py
devinterp/test_utils.py
devinterp/utils.py
devinterp/vis_utils.py
devinterp/backends/__init__.py
devinterp/backends/default/__init__.py
devinterp/backends/default/slt/__init__.py
devinterp/backends/default/slt/sampler.py
devinterp/backends/tpu/__init__.py
devinterp/backends/tpu/slt/__init__.py
devinterp/backends/tpu/slt/sampler.py
devinterp/mechinterp/__init__.py
devinterp/mechinterp/activations.py
devinterp/mechinterp/hooks.py
devinterp/optim/__init__.py
devinterp/optim/preconditioner.py
devinterp/optim/prior.py
devinterp/optim/sgld.py
devinterp/optim/sgmcmc.py
devinterp/optim/sgnht.py
devinterp/optim/utils.py
devinterp/slt/__init__.py
devinterp/slt/callback.py
devinterp/slt/cov.py
devinterp/slt/gradient.py
devinterp/slt/llc.py
devinterp/slt/loss.py
devinterp/slt/mala.py
devinterp/slt/norms.py
devinterp/slt/sampler.py
devinterp/slt/trace.py
devinterp/slt/wbic.py
devinterp-1.3.2.dist-info/METADATA
devinterp-1.3.2.dist-info/WHEEL
devinterp-1.3.2.dist-info/top_level.txt
devinterp-1.3.2.dist-info/RECORD
