Metadata-Version: 2.2
Name: devinterp
Version: 1.3.2
Summary: A library for doing research on developmental interpretability
Project-URL: Homepage, https://github.com/timaeus-research/devinterp
Project-URL: Bug Tracker, https://github.com/timaeus-research/devinterp/issues
Classifier: Programming Language :: Python :: 3.8
Classifier: Programming Language :: Python :: 3.9
Classifier: Programming Language :: Python :: 3.10
Classifier: Programming Language :: Python :: 3.11
Classifier: Operating System :: OS Independent
Requires-Python: >=3.8
Requires-Dist: einops>=0.6.1
Requires-Dist: matplotlib>=3.7.5
Requires-Dist: numpy>=1.23.5
Requires-Dist: pandas>=1.5.3
Requires-Dist: torch>=2.0.1
Requires-Dist: tqdm>=4.65.0
Requires-Dist: cloudpickle>=3.0.0
Provides-Extra: dev
Requires-Dist: pytest==7.4.3; extra == "dev"
Requires-Dist: transformers; extra == "dev"
Requires-Dist: datasets; extra == "dev"
Requires-Dist: transformer_lens; extra == "dev"
Requires-Dist: syrupy; extra == "dev"
Provides-Extra: docs
Requires-Dist: sphinx; extra == "docs"
Requires-Dist: sphinx-math-dollar; extra == "docs"
Requires-Dist: sphinx-rtd-theme; extra == "docs"
Requires-Dist: sphinx-autobuild; extra == "docs"
Requires-Dist: myst_parser; extra == "docs"
Provides-Extra: vis
Requires-Dist: plotly>=5.20.0; extra == "vis"
